pandasaurus_cxg/__init__.py
pandasaurus_cxg/anndata_analyzer.py
pandasaurus_cxg/anndata_enricher.py
pandasaurus_cxg/enrichment_analysis.py
pandasaurus_cxg/graph_generator/__init__.py
pandasaurus_cxg/graph_generator/graph_generator.py
pandasaurus_cxg/graph_generator/graph_generator_utils.py
pandasaurus_cxg/graph_generator/graph_namespaces.py
pandasaurus_cxg/graph_generator/graph_predicates.py
pandasaurus_cxg/schema/__init__.py
pandasaurus_cxg/schema/cell_x_gene_schema.py
pandasaurus_cxg/utils/__init__.py
pandasaurus_cxg/utils/anndata_loader.py
pandasaurus_cxg/utils/exceptions.py
pandasaurus_cxg/utils/logging_config.py
pandasaurus_cxg-0.2.3.dist-info/LICENSE
pandasaurus_cxg-0.2.3.dist-info/METADATA
pandasaurus_cxg-0.2.3.dist-info/WHEEL
pandasaurus_cxg-0.2.3.dist-info/RECORD
