Metadata-Version: 2.1
Name: pandasaurus-cxg
Version: 0.2.3
Summary: Ontology enrichment tool for CxG standard AnnData files.
License: http://www.apache.org/licenses/LICENSE-2.0
Author: Ugur Bayindir
Author-email: ugur@ebi.ac.uk
Requires-Python: >=3.9,<4.0
Classifier: License :: Other/Proprietary License
Classifier: Programming Language :: Python :: 3
Classifier: Programming Language :: Python :: 3.9
Classifier: Programming Language :: Python :: 3.10
Classifier: Programming Language :: Python :: 3.11
Classifier: Programming Language :: Python :: 3.12
Classifier: Programming Language :: Python :: 3.13
Provides-Extra: docs
Requires-Dist: anndata (>=0.10.5,<0.11.0)
Requires-Dist: matplotlib (>=3.7.2,<4.0.0)
Requires-Dist: oaklib (==0.5.25)
Requires-Dist: pandas (>=2.0.2,<3.0.0)
Requires-Dist: pandasaurus (>=0.3.8,<0.4.0)
Requires-Dist: pygraphviz (>=1.11,<2.0)
Requires-Dist: rdflib (>=6.3.2,<7.0.0)
Requires-Dist: sphinx (>=7.2.6,<8.0.0) ; extra == "docs"
Requires-Dist: sphinx-copybutton (>=0.5.2,<0.6.0) ; extra == "docs"
Requires-Dist: sphinx-rtd-theme (>=1.3.0,<2.0.0) ; extra == "docs"
